notes_to_keep/__init__.py
notes_to_keep/gkeep.py
notes_to_keep/note.py
notes_to_keep/notes_to_keep.py
notes_to_keep/scan_notes.py
notes_to_keep-0.0.4.dist-info/LICENSE
notes_to_keep-0.0.4.dist-info/METADATA
notes_to_keep-0.0.4.dist-info/WHEEL
notes_to_keep-0.0.4.dist-info/entry_points.txt
notes_to_keep-0.0.4.dist-info/top_level.txt
notes_to_keep-0.0.4.dist-info/RECORD
